[
  {
    "sku": null,
    "autoDiscover": false,
    "createdAt": "2016-10-10T14:03:28.799Z",
    "identifiers": [
      "c0:3f:d5:63:fe:13"
    ],
    "name": "c0:3f:d5:63:fe:13",
    "relations": [],
    "tags": [
      "unavailable",
      "vm_cid-fake_uuid",
      "disk_cid-fake_uuid"
    ],
    "type": "compute",
    "updatedAt": "2016-10-24T15:45:28.938Z",
    "id": "57fb9fb03fcc55c807add41c",
    "persistent_disk": {
      "pregenerated_disk_cid": "57fb9fb03fcc55c807add41c-id",
      "disk_cid": "",
      "location": "/dev/sdb",
      "attached": false
    }
  }
]
